{
  "unversionedId": "lunar_starship/lunar_starship",
  "id": "lunar_starship/lunar_starship",
  "title": "Lunar Starship Optimal Control Example Using CITROS",
  "description": "This Lunar Starship mission project addresses the lunar hopper challenge by optimizing the ascent, ballistic flight and landing process on the Moon's surface, aiming to minimize fuel consumption, time, or other relevant parameters. It empowers users to define both theoretical and real dynamic functions, enhancing prediction accuracy and enabling real-time corrections during lunar mission.",
  "source": "@site/docs_tutorials/lunar_starship/lunar_starship.md",
  "sourceDirName": "lunar_starship",
  "slug": "/lunar_starship/",
  "permalink": "/doc/docs_tutorials/lunar_starship/",
  "draft": false,
  "tags": [],
  "version": "current",
  "sidebarPosition": 70,
  "frontMatter": {
    "sidebar_position": 70,
    "sidebar_label": "Lunar Starship"
  },
  "sidebar": "tutorialSidebar",
  "previous": {
    "title": "Lunar Hopper",
    "permalink": "/doc/docs_tutorials/lunar_hopper/"
  },
  "next": {
    "title": "SpiceyPy Using CITROS",
    "permalink": "/doc/docs_tutorials/spiceypy/"
  }
}