{
  "unversionedId": "data_access/repository_overview",
  "id": "data_access/repository_overview",
  "title": "Repository Overview",
  "description": "Information about repositories",
  "source": "@site/docs_data_analysis/data_access/repository_overview.md",
  "sourceDirName": "data_access",
  "slug": "/data_access/repository_overview",
  "permalink": "/docs/docs_data_analysis/next/data_access/repository_overview",
  "draft": false,
  "tags": [],
  "version": "current",
  "sidebarPosition": 2,
  "frontMatter": {
    "toc_max_heading_level": 4,
    "hide_title": true,
    "sidebar_position": 2,
    "sidebar_label": "Repository Overview",
    "description": "Information about repositories"
  },
  "sidebar": "dataAnalysisSidebar",
  "previous": {
    "title": "Getting Started",
    "permalink": "/docs/docs_data_analysis/next/data_access/getting_started"
  },
  "next": {
    "title": "Batch Overview",
    "permalink": "/docs/docs_data_analysis/next/data_access/batch_overview"
  }
}